[
  {
    "metadata": {
      "versions": "templates/kernel.json"
    },
    "name": "kernel",
    "py/object": "pros.conductor.templates.base_template.BaseTemplate",
    "target": "v5",
    "tags": "test pros",
    "repository": "purduesigbots/pros"
  },
  {
    "metadata": {
      "versions": "templates/okapilib.json"
    },
    "name": "okapilib",
    "py/object": "pros.conductor.templates.base_template.BaseTemplate",
    "target": "v5",
    "tags": "test pros",
    "repository": "purduesigbots/OkapiLib"
  },
  {
    "metadata": {
      "versions": "pros-branchline/templates/arms.json"
    },
    "name": "arms"
  }
]